credo/__init__.py
credo/banks_and_currencies.py
credo/customers.py
credo/direct_charge.py
credo/payment.py
credo/payment_link.py
credo/products.py
credo/subaccounts.py
credo/transactions.py
credo_python-1.0.1.dist-info/LICENSE
credo_python-1.0.1.dist-info/METADATA
credo_python-1.0.1.dist-info/WHEEL
credo_python-1.0.1.dist-info/top_level.txt
credo_python-1.0.1.dist-info/RECORD
