Metadata-Version: 2.1
Name: credo-python
Version: 1.0.1
Summary: A Python Wrapper for the Credo API
Home-page: https://github.com/BdVade/credo-python
Author: Aderibigbe Victor
Author-email: victoraderibigbe03@gmail.com
License: MIT
Keywords: credo,python,sdk
Platform: UNKNOWN
Classifier: License :: OSI Approved :: MIT License
Classifier: Programming Language :: Python :: 3
Classifier: Programming Language :: Python :: 3.8
Classifier: Intended Audience :: Developers
Classifier: Topic :: Software Development :: Build Tools
License-File: LICENSE
Requires-Dist: requests
